{
    "baseurl": "https://active-cod.cloudvent.net",
    "site_short_title": "Powerlife",
    "site_title": "Gesundheitspraxis Zug - Powerlife",
    "description": "Powerlife® an der Bahnhofstrasse 25 in Zug arbeitet mit viel Kompetenz, Engagement und Begeisterung daran, Gesundheit zu bewirken und den Kunden zu innerer und äusserer Balance zu verhelfen.",
    "favicon_icon": "/images/favicon.ico",
    "favicon_image": "/images/favicon.png",
    "image": "/uploads/logo-new.png",
    "image_alt": "Powerlife"
}
